teedoc_plugin_google_analytics/__init__.py
teedoc_plugin_google_analytics-1.0.1.dist-info/LICENSE
teedoc_plugin_google_analytics-1.0.1.dist-info/METADATA
teedoc_plugin_google_analytics-1.0.1.dist-info/WHEEL
teedoc_plugin_google_analytics-1.0.1.dist-info/top_level.txt
teedoc_plugin_google_analytics-1.0.1.dist-info/RECORD
