Metadata-Version: 2.1
Name: teedoc-plugin-google-analytics
Version: 1.0.1
Summary: google analytics plugin for teedoc
Home-page: https://github.com/Neutree/teedoc
Author: Neucrack
Author-email: CZD666666@gmail.com
License: MIT
Keywords: google analytics teedoc plugin
Platform: UNKNOWN
Classifier: Intended Audience :: Developers
Classifier: License :: OSI Approved :: MIT License
Classifier: Programming Language :: Python :: 3
